mkdocs_png_to_webp/__init__.py
mkdocs_png_to_webp/plugin.py
mkdocs_png_to_webp-0.0.3.dist-info/LICENSE
mkdocs_png_to_webp-0.0.3.dist-info/METADATA
mkdocs_png_to_webp-0.0.3.dist-info/WHEEL
mkdocs_png_to_webp-0.0.3.dist-info/entry_points.txt
mkdocs_png_to_webp-0.0.3.dist-info/top_level.txt
mkdocs_png_to_webp-0.0.3.dist-info/RECORD
