Metadata-Version: 2.1
Name: mkdocs-png-to-webp
Version: 0.0.3
Summary: A package to convert your mkdocs images from png to webp
Home-page: https://github.com/mur4d1n-lib/mkdocs-png-to-webp/
Author: mur4d1n
Author-email: mur4d1n@yandex.ru
Classifier: Programming Language :: Python :: 3.9
Classifier: License :: OSI Approved :: GNU General Public License v3 (GPLv3)
License-File: LICENSE
Requires-Dist: pip (>=22)
Requires-Dist: mkdocs (>=1)
Requires-Dist: webptools (==0.0.9)
